Workbook

Sheet PRESUPUESTOS
A1: Nº | B1: FECHA | C1: CLIENTE | D1: EQUIPO - PATENTE | E1: DESCRIPCION | F1: A FACTURAR | G1: ESTADO | H1: OBSERVACIONES
A2: 248 | C2: INDUMAT V.C | D2: MV41 | F2: NO APROBADO | G2: NO APROBADO
A3: 2 | C3: INDUMAT | D3: JETSTREAM GAP01 | F3: NO APROBADO | G3: NO APROBADO
A4: 230 | B4: 45338 | C4: TRES ARROYOS | D4: - | E4: MANGUERA DESOBSTRUCTORA | F4: $ 6.006.056,81 | G4: APROBADO | H4: PAGADO, FINALIZADO.
A5: 1 | C5: SYL | D5: FURGON CHEVY VAN 30 | F5: $ 485.000,00 | G5: APROBADO
A6: 238 | B6: 45373 | C6: ABSA - LA PLATA | D6: AA-247-RA | F6: NO APLICA | G6: APROBADO | H6: SE VA PASAR EL PRESUPUESTO HASTA DONDE SE HIZO Y QUEDAN PENDIENTE ALGUNOS REPUESTOS PARA LA FINALIZACION
A7: 241 | B7: 45300 | C7: ABSA - LA PLATA | D7: AA-717-YH | F7: NO APLICA | G7: APROBADO | H7: TIENE QUE VOLVER A FORD PARA UN SENSOR (ESPERANDO RESPUESTA DE FORD)
A8: 245 | C8: SYL (La Plata) | D8: MV29 | F8: CLIENTE INTERNO | G8: COTIZADO
A9: 247 | C9: SYL (La Plata) | D9: MV26 | F9: CLIENTE INTERNO | G9: COTIZADO
A10: 242 | C10: ABSA | D10: AA-717-YL | E10: SE REALIZO UNA INSPECCION PARCIAL EN LA PLATA DE ABSA LA PLATA (SIN EFECTO, SE COBRA TODO JUNTO CON ACARREO) | F10: NO APLICA | G10: SIN EFECTO | H10: SE REALIZO UNA INSPECCION PARCIAL EN LA PLATA DE ABSA LA PLATA (SIN EFECTO, SE COBRA TODO JUNTO CON ACARREO)
A11: 246 | C11: SYL (La Plata) | D11: MV 25 | F11: PENDIENTE | G11: COTIZADO
A12: 243 | C12: ABSA | D12: AA-717-YM | E12: SE REALIZO UNA INSPECCION PARCIAL EN LA PLATA DE ABSA LA PLATA (SIN EFECTO, SE COBRA TODO JUNTO CON ACARREO) | F12: NO APLICA | G12: SIN EFECTO | H12: SE REALIZO UNA INSPECCION PARCIAL EN LA PLATA DE ABSA LA PLATA (SIN EFECTO, SE COBRA TODO JUNTO CON ACARREO)
A13: 244 | C13: ABSA | D13: ACARREO Y INSPECCION | E13: ACARREO Y INSPECCION DE CAMIONES DE ABSA (AA-717-YL, AA-717-YM) ESPERANDO CONFIRMACION | F13: 1.395.900 | G13: SIN EFECTO | H13: ACARREO Y INSPECCION DE CAMIONES DE ABSA (AA-717-YL, AA-717-YM) ESPERANDO CONFIRMACION
A14: 249 | B14: 45355 | C14: ABSA - REGION 5 | D14: AA-698-SW | E14: ARREGLO EN GENERAL, EN REPARACION | F14: ENVIADO | G14: APROBADO
A15: 250 | C15: SyL | D15: MV21 | F15: PENDIENTE | G15: COTIZADO
A16: 251 | B16: 45387 | C16: MUNI BERAZATEGUI | D16: VACTOR 2100 | E16: COTIZACION DE REPUESTO COLLAR ASSEMBLY TWIN DISC, ESPERANDO REPUESTA DEL CLIENTE | F16: 1400908.1 | G16: SIN EFECTO
A17: 252 | C17: MUNI MAR DEL PLATA | D17: JET-VAC 4075 | E17: MANGUERAS Y ACOPLES (CONCURSO DE PRECIOS, ESPERANDO RESPUESTA) | F17: 11637840 | G17: SIN EFECTO
A18: 253 | B18: 45483 | C18: MUNI MAR DEL PLATA OSSE | D18: JET-VAC 4075/4500 | E18: FILTROS Y VALVULAS | F18: ? | G18: COTIZADO
A19: 254 | C19: AGUAS RIONEGRINAS | D19: NO ESPECIFICO | E19: TOBERA SAPO 1" , ENVIADO ESPERANDO RESPUESTA. | F19: 366773 | G19: SIN EFECTO
A20: 255 | C20: ABSA | D20: JET-VAC 4075 | E20: ACARREO Y INSPECCION DE CAMIONES DE ABSA (AA-717-YL, AA-717-YM) | F20: 1395000 | G20: SIN EFECTO
A21: 256 | B21: 45426 | C21: SERVICOOP | D21: - | E21: MANGUERA DESOB 1" Y 3/4" | F21: $9.023.300,00 | G21: SIN EFECTO
A22: 257 | C22: INDUMAT | D22: PLANCHUELA | F22: 372000 | G22: SIN EFECTO
A23: 258 | C23: ABSA - LINCOLN | D23: JET VAC 4075 - AA-717-YI | E23: ARREGLOS EN GENERAL | F23: 20734574 | G23: APROBADO
A24: 259 | C24: FLUVIOMAT | D24: NO APLICA | F24: NO APLICA | G24: COTIZADO
A25: 260 | C25: INDUMAT | D25: MV09 | F25: NO APLICA | G25: SIN EFECTO
A26: 261 | C26: ABSA | D26: - | E26: MANGUERA DESOBSTRUCTORA 1" X 150MTS | F26: $6.460.238 | G26: COTIZADO
A27: 262 | C27: HR INDUSTRIAL | D27: NO APLICA | F27: $7.000.000 | G27: SIN EFECTO
A28: 263 | B28: 45441 | C28: SERVICIOS IBARRA | D28: - | E28: REJA CANASTO Y BOYA | F28: $800.000 (+IVA) | G28: APROBADO
A29: 264 | C29: INDUMAT | D29: MV33 | F29: $ 2.257.200,00
A30: 265 | B30: 45439 | C30: OSSE | D30: NO ESPECIFICO | E30: BOMBA KS40 | F30: $19.132.219,92 | G30: COTIZADO
A31: 266 | C31: ABSA | D31: 4075 (AA-717-YL) (AA-717-YM) | E31: ACARREO DE CAMIONES | F31: $880.000 (+IVA) | G31: APROBADO | H31: OC RECIBIDA EL 7/8 , FC ENVIADA
A32: 267 | B32: 45453 | C32: BENITO ROGGIO | D32: JET-VAC 5010 CB | E32: EQUIPO 0KM (4 CAMIONES) CONFIGURACION A | F32: USD 263.310 | G32: COTIZADO
A33: 268 | B33: 45453 | C33: BENITO ROGGIO | D33: JET-VAC 5010 CB | E33: EQUIPO 0KM (4 CAMIONES) CONFIGURACION B | F33: USD 275.563 | G33: COTIZADO
A34: 269 | B34: 45453 | C34: BENITO ROGGIO | D34: JET-VAC 5010 CB | E34: EQUIPO 0KM (4 CAMIONES) CONFIGURACION C | F34: USD 292.514 | G34: COTIZADO
A35: 270 | C35: AGUASSANTAFESINAS | D35: - | E35: 4 MANGUEROTES DE 8" | G35: SIN EFECTO
A36: 271 | C36: ABSA - LA PLATA | D36: AA-717-YH | E36: TERCERIZADO FORD CIRCUITO DE COMBUSTIBLE | F36: $1.980.000 | G36: APROBADO
A37: 272 | C37: INDUMAT | D37: FTS-456 | F37: 216HS | G37: COTIZADO
A38: 273 | C38: M. JUNIN | D38: Hidro JET 4500 | E38: MANGUERA DESOBSTRUCTORA 1" X 150MTS Y 3/4 MARCA ZEC ITALIA | F38: 14031084 | G38: SIN EFECTO
A39: 274 | C39: M.BERAZATEGUI | D39: JET-VAC 4075 | E39: RELAY 12V | F39: 471429 | G39: APROBADO
A40: 275 | C40: AUTOMAT - OBRAS | D40: CARRETON | F40: 1585644 | G40: COTIZADO
A41: 276 | C41: ABSA - CAÑUELAS | D41: JET-VAC 4075 | E41: SOPLADOR REPYCKY R3.8 (BLOWER) | F41: 34449607 | G41: COTIZADO | H41: BLOWER NUVO PARA EQUIPO AA-698-SW
A42: 277 | C42: HR INDUSTRIAL | D42: VACTOR 2100 | E42: CORONA DE GIRO DE CARRETEL VACTOR | F42: $7.223.437 | G42: SIN EFECTO
A43: 278 | C43: OSSE | D43: REPUESTOS VARIOS | G43: COTIZADO
A44: 279 | C44: AGUAS RIONEGRINAS | D44: VACTOR 2100 | E44: ENGRANAJES DE CAJA COTTA | F44: USD19.833 | G44: APROBADO
A45: 280 | C45: M. JUNIN | D45: JET VAC 4075? | E45: MANGUERA DESOBSTRUCTORA 1" | F45: $7.754.020 | G45: APROBADO
A46: 281 | C46: OSSE | D46: JET-VAC 4075 | E46: BURLETE DE SELLO DE TANQUE | F46: 665400 | G46: APROBADO
A47: 282 | C47: SAMSA | D47: HIDROVACUO | E47: TOBERAS | F47: 2160404 | G47: SIN EFECTO
A48: 283 | C48: SUMMIT NQN SA | D48: JET-VAC 5010 CB | E48: JET-VAC 5010 CB | F48: USD 263.310 | G48: COTIZADO | H48: EQUIPOS 0KM
A49: 284 | C49: SUMMIT NQN SA | D49: JET-VAC 5010 CB | E49: JET-VAC 5010 CB | F49: USD 275.563 | G49: COTIZADO | H49: EQUIPOS 0KM
A50: 285 | C50: SUMMIT NQN SA | D50: JET-VAC 5010 CB | E50: JET-VAC 5010 CB | F50: USD 292.514 | G50: COTIZADO | H50: EQUIPOS 0KM
A51: 286 | C51: OSSE | D51: JET-VAC 4500-D | E51: FILTRO ACERO INOXIDABLE, RETENCION 200 MICRONES DE 70 H: 138MM ESTAÑADO | F51: 568200 | G51: APROBADO
A52: 287 | C52: M.JUNIN | D52: JET-VAC 4500-D | E52: FILTRO ACERO INOXIDABLE, RETENCION 200 MICRONES DE 70 H: 138MM ESTAÑADO, VALVULA DESVIAORA | F52: 1642817 | G52: APROBADO | H52: CONCRETADO!
A53: 288 | C53: AGUAS RIONEGRINAS | D53: VACTOR 2100 | E53: EMBRAGUE CAJA COTA | F53: USD 4.790 | G53: APROBADO | H53: CONCRETADO!
A54: 289 | C54: SERVICIOS IBARRA | D54: JET-VAC 4075 | E54: TANQUE DE AGUA LADO ACOMPAÑANTE SUPERIOR | F54: USD7400 | G54: COTIZADO
A55: 290 | B55: 45525 | C55: ABSA - LAS FLORES | D55: HIDROJET- SCORZA | E55: INSPECCION DE ARREGLOS EN GENERAL | F55: 34101996 | G55: APROBADO | H55: ADAPTACION DE BOMBA Y ARREGLOS EN GENERAL
A56: 291 | B56: 45525 | C56: M.JUNIN | D56: JET-VAC-4075 | E56: INSPECCION Y ARREGLOS EN GENERAL | F56: 33505599 | G56: APROBADO | H56: REPARACIONES EN GENERAL
A57: 292 | B57: 45526 | C57: M. Trenque Lauquen | D57: SCORZA | E57: MANGUERA DESOBSTRUCTORA 1" | F57: 8537501 | G57: COTIZADO | H57: EN EL PRECIO ESTA INCLUIDO EL ENVIO
A58: 293 | B58: 45527 | C58: M.JUNIN | D58: JET-VAC 4075 | E58: TOBERAS, GRANADA OVOIDAL 3/4 | F58: 1171799 | G58: APROBADO | H58: DOS TOBERAS GRANADA Y UNA OVOIDAL
A59: 294 | B59: 45532 | C59: M.BERAZATEGUI | D59: VACTOR 2100 | E59: REPARACION BOMBA DE AGUA | F59: 1176985 | G59: APROBADO | H59: ESPERANDO PAGO
A60: 295 | B60: 45545 | C60: AGUAS RIONEGRINAS | D60: ABROCHADORA HIDRAULICA | E60: PRENSA PARA MANGUERAS HIDRAULICAS IN SITU | G60: COTIZADO | H60: SE COTIZO 3 OPCIONES DISTINTAS, ESPERANDO QUE DEFINA CUAL ES DE SU INTERES
A61: 296 | B61: 45545 | C61: AESA (YFP) | D61: JET-VAC 5010-CB | E61: CONFIGURACION A | F61: USD 263.310 | G61: COTIZADO | H61: EQUIPO 0KM
A62: 297 | B62: 45545 | C62: AESA (YFP) | D62: JET-VAC 5010-CB | E62: CONFIGURACION B | F62: USD 275.563 | G62: COTIZADO | H62: EQUIPO 0KM
A63: 298 | B63: 45545 | C63: AESA (YFP) | D63: JET-VAC 5010-CB | E63: CONFIGURACION C | F63: USD 292.514 | G63: COTIZADO | H63: EQUIPO 0KM
A64: 299 | B64: 45552 | C64: EMSADE | D64: MANGUERA 1" | E64: MANGUERA DESOBSTRUCTORA 1" | F64: 8733415 | G64: COTIZADO | H64: MANGUERA DESOBSTRUCTORA
A65: 300 | B65: 45558 | C65: AGUAS DE FORMOSA | D65: N/A | E65: MANGUERA DE 12" | F65: USD 13.830 | G65: COTIZADO | H65: MANGUEROTE 12"
A66: 301 | B66: 45560 | C66: ABSA-CAÑUELAS | D66: JET-VAC 4075 | E66: CILINDRO DE TANQUE | F66: 6551015 | G66: COTIZADO | H66: CILINDRO ELEVACION TANQUE DE EQUIPO JET-VAC 4075
A67: 302 | B67: 45568 | C67: AESA (YFP) | D67: JET-VAC 5010 CB | E67: EQUIPO JET-VAC 5010 CB | F67: USD 250.121 | G67: COTIZADO | H67: EQUIPO 0KM
A68: 303 | B68: 45569 | C68: OSSE | D68: JET-VAC 4500-D | E68: CODO GIRATORIO | F68: 2855352 | G68: COTIZADO | H68: CODO GIRATORIO
A69: 304 | B69: 45569 | C69: OSSE | D69: JET-VAC 4500-D | E69: VALVULA DE TRES VIAS | F69: 501136 | G69: COTIZADO | H69: VALVULA DESVIADORA TRES VIAS
A70: 305 | B70: 45569 | C70: SAMSA | D70: NO ESPECIFICO | E70: MANGUERA DESOBSTRUCTORA 1" | F70: 8100053 | G70: COTIZADO | H70: MANGUERA DESOBTRUCTORA 1"
A71: 306 | B71: 45570 | C71: AGUAS RIONEGRINAS | D71: JET-VAC 5010 | E71: EQUIPO JET-VAC 5010 CB CONFIGURACION A | F71: USD 242.739 | G71: COTIZADO | H71: EQUIPO 0KM
A72: 307 | B72: 45570 | C72: AGUAS RIONEGRINAS | D72: JET-VAC 5010 | E72: EQUIPO JET-VAC 5010 CB CONFIGURACION B | F72: USD 254.034 | G72: COTIZADO | H72: EQUIPO 0KM
A73: 308 | B73: 45570 | C73: AGUAS RIONEGRINAS | D73: JET-VAC 5010 | E73: EQUIPO JET-VAC 5010 CB CONFIGURACION C | F73: USD 269.661 | G73: COTIZADO | H73: EQUIPO 0KM
A74: 309 | B74: 45573 | C74: HR INDUSTRIAL | D74: REPUESTO | E74: VACTOR 2100 | F74: 7945780 | G74: COTIZADO | H74: RODAMIENTO PARA CARRETEL VACTOR
A75: 310 | B75: 45582 | C75: ABSA - LA PLATA | D75: JET-VAC 4075 | E75: ARREGLOS EN GENERAL | F75: 22243813 | G75: APROBADO | H75: REPARACION DE EMBRAGUE Y ARREGLOS EN GENERAL
A76: 311 | B76: 45587 | C76: MUNICIPALIDAD DE SALADILLO | D76: NO ESPECIFICO | E76: MANGUERA , TOBERAS | F76: 20872166 | G76: COTIZADO | H76: MANGUERAS DESOB DE 1" Y 3/4 MARCA ZEC
A77: 312 | B77: 45589 | C77: OSSE | D77: JET-VAC 4500-D | E77: CODO GIRATORIO 1" | F77: 3454975 | G77: COTIZADO | H77: DOS CODOS GIRATORIOS DE 1" PARA EQUIPO JET-VAC 4500-D
A78: 313 | B78: 45589 | C78: SCPL | D78: ITECSA | E78: TOBERAS Y ABRAZADERAS | F78: 9869493 | G78: APROBADO | H78: MANGUERAS DESOB DE 1", TOBERAS, ABRAZADERAS, MANGUEROTE 8" 7m
A79: 314 | B79: 45596 | C79: M.BERAZATEGUI | D79: VACTOR 2100 | E79: REPARACION DE BOMBA RODER | F79: 3870363 | G79: APROBADO | H79: REPARACION EN GENERAL DE BOMBA
A80: 315 | B80: 45601 | C80: ABSA - LA PLATA | D80: JET-VAC 4075 | E80: REPARACION EN GENERAL | F80: 28553207 | G80: APROBADO | H80: REPARACION EN GENERAL PARA EQUIPO
A81: 316 | B81: 45602 | C81: MUNICIPALIDAD DE JUNIN | D81: JET-VAC 4500-D | E81: MANGUERA DE 3/4 DESOBSTRUCTORA | F81: 7612098 | G81: COTIZADO | H81: MANGUERA DE CARRETEL
A82: 317 | B82: 45608 | C82: MUNICIPALIDAD TRES ARROYOS | D82: VACTOR 2100 | E82: REPARACION EN GENERAL | F82: 18164210 | G82: APROBADO | H82: REPARACION DE EQUIPO EN GENERAL
A83: 318 | B83: 45609 | C83: OSSE | D83: NO ESPECIFICO | E83: MANGUEROTE DE SUBCCION 8" | F83: 870295 | G83: COTIZADO | H83: MANGUEROTE DE PLUMA
A84: 319 | B84: 45615 | C84: AGUAS RIONEGRINAS | D84: NO ESPECIFICO | E84: CODO GIRATORIO 1" , MANGUEROTE DE 8" | F84: 1994726 | G84: COTIZADO | H84: CODO GIRATORIO Y MANGUEROTE DE SUBCCION DE PLUMA
A85: 320 | B85: 45660 | C85: MUNICIPALIDAD DE JUNIN | D85: HIDROJET 4500 | E85: MANGUERA 3/4 DESOB | F85: 8492882 | G85: COTIZADO | H85: MANGUERA PARA HIDROJET 4500-D
... A87: 322 | B87: 46760 | C87: ABSA - LINCONL | D87: JET-VAC 4075 | E87: VALVULA Y CODO GIRATORIO | F87: 3687332 | G87: APROBADO | H87: CAMBIO DE CODO GIRATORIO Y VALVULAS
A88: 323 | B88: 45671 | C88: OSSE | D88: NO ACLARA | E88: MANGUERA 3/4 DESOB Y TOBERAS | F88: 9003266 | G88: COTIZADO
A89: 324 | B89: 45306 | C89: ADESSOTECH | D89: ECONOVO | E89: TOBERA ALUMINIO 1" | F89: 1500333 | G89: APROBADO | H89: UNA TOBERA DE ALUMINIO
A90: 325 | B90: 45679 | C90: AUAS RIONEGRINAS | D90: VACTOR 2100 | E90: PUNTERAS Y ABRAZADERAS RAPIDAS 8" | F90: 1400293 | G90: COTIZADO
A91: 326 | B91: 45685 | C91: SERVICIOS IBARRA | D91: JET-VAC 4075 | E91: TANQUE DE AGUA LADO CHOFER | F91: 9580780 | G91: APROBADO | H91: COLOCACION DE TANQUE MAS SUNCHO
A92: 327 | B92: 45698 | C92: ABSA - LINCONL | D92: JET-VAC 4075 | E92: TAPA DE TANQUE DESPERDICIO | F92: 15584770 | G92: APROBADO | H92: FABRICACION DE TANQUE DE DESPERDICIO
A93: 328 | B93: 45698 | C93: AGUAS RIONEGRINAS | D93: AQUATECH | E93: INSPECCION IN SITU NEUQUEN | F93: 3274580 | G93: COTIZADO | H93: 2 TECNICOS VIAJAN A NEUQUEN PARA DIAGNOSTICO DE EQUIPO
A94: 329 | B94: 45713 | C94: OSSE | D94: JET-VAC 4500-D | E94: CODO GIRATORIO 1" Y VALVULA ESFERICA 3 VIAS 1" | F94: 7920514 | G94: COTIZADO | H94: 5 ITEMS DE CADA UNO
A95: 330 | B95: 45716 | C95: MUNICIPALIDAD DE JUNIN | D95: JET-VAC 4500-D | E95: MANGUERA DESOBSTRUCTORA | F95: 8482882 | G95: APROBADO | H95: MANGUERA DESOB 3/4
A96: 331 | B96: 45726 | C96: AGUAS RIONEGRINAS | D96: VACTOR 2100 | E96: BOMBA RODDER | F96: 85522500 | G96: COTIZADO | H96: VENTA DE BOMBA NUEVA
A97: 332 | B97: 45728 | C97: AGUAS RIONEGRINAS | D97: AQUATECH | E97: REPARACIONES EN GENERAL | F97: 40739989 | G97: APROBADO | H97: PROBLEMAS EN GENERAL
A98: 333 | B98: 45733 | C98: SASU INDUSTRIAL | D98: NO ACLARA | E98: TOBERAS | F98: 10122286 | G98: COTIZADO | H98: TOBERAS VARIAS
A99: 334 | B99: 45733 | C99: SAMSA | D99: NO ACLARA | E99: TOBERAS | F99: 2710167 | G99: APROBADO | H99: TOBERAS VARIAS
A100: 335 | B100: 45735 | C100: MUNICIPALIDAD DE JUNIN | D100: JET-VAC 4075 | E100: REDUCTOR DE 8" A 6" | F100: 3637518.9 | G100: COTIZADO | H100: REDUCTOR DE MANGUERA DE 8" A 6"
A101: 336 | B101: 45741 | C101: AGUAS RIONEGRINAS | D101: VACTOR 2100 | E101: ADAPTACION BOMBA DE AGUA | F101: 45785 | G101: COTIZADO | H101: ADAPTACION BOMBA DE AGUA PRATISSOLI (USD)
...

Sheet VENTAS
A1: DOMINIO / CC | B1: Nº | C1: FECHA COTIZACION | D1: FECHA DE OC | E1: FECHA FACTURA | F1: FECHA COBRO | G1: FECHA DE ENTREGA | H1: CLIENTE | I1: DESCRIPCION INICIAL | J1: COSTO | K1: BENEFICIO ANTES IMP (%) | L1: BENEFICIO DESPUES IMP ($) | M1: A COBRAR STD | N1: A COBRAR REAL | O1: ESTADO | P1: DESCRIPCION FINAL | Q1: HS COTIZADAS | R1: HS UTILIZADAS | S1: POLIZA | T1: ESTADO DE POLIZA | U1: OC Nº | V1: FC Nº | W1: FECHA FINALIZACION | X1: Nº DE REMITO
A2: AA-717-YM | B2: 310 | C2: 45617 | D2: 45665 | E2: 45695 | G2: 45810 | H2: =VLOOKUP($B2,PRESUPUESTOS!$A$4:$H$1026,3,FALSE()) -> ABSA - LA PLATA | I2: =VLOOKUP($B2,PRESUPUESTOS!$A$4:$H$1026,5,FALSE()) -> ARREGLOS EN GENERAL | J2: 5136802 | K2: 69.75 | L2: =M2*K2/100*0.65 -> 10083887 | M2: =J2*1.05/(1-0.04-0.012-0.008-K2/100) -> 22241823 | N2: 22243813 | O2: PAGADO | P2: ARREGLOS EN GENERAL | Q2: 194 | R2: 227 | S2: SI | T2: FINALIZADA 23/07/25 | U2: 4500025133 | V2: FACA0000300000037 | W2: 45782 | Z2: finalizado
A3: AA-717-YL | B3: 315 | C3: 45617 | D3: 45665 | E3: 45695 | G3: 45810 | H3: =VLOOKUP($B3,PRESUPUESTOS!$A$4:$H$1026,3,FALSE()) -> ABSA - LA PLATA | I3: =VLOOKUP($B3,PRESUPUESTOS!$A$4:$H$1026,5,FALSE()) -> REPARACION EN GENERAL | J3: 3898795 | K3: 72.3 | L3: =M3*K3/100*0.65 -> 8865671.2 | M3: =J3*1.05/(1-0.04-0.012-0.008-K3/100) -> 18865137 | N3: 18883614 | O3: PAGADO | P3: ARREGLOS EN GENERAL | Q3: 107 | R3: 260 | S3: SI | T3: FINALIZADA 23/07/25 | U3: 4500025133 | V3: FACA0000300000037 | W3: 45813 | Z3: en reparacion
A4: DAT-754 | B4: 317 | C4: 45688 | D4: 45713 | E4: 45729 | G4: 45729 | H4: =VLOOKUP($B4,PRESUPUESTOS!$A$4:$H$1026,3,FALSE()) -> MUNICIPALIDAD TRES ARROYOS | I4: =VLOOKUP($B4,PRESUPUESTOS!$A$4:$H$1026,5,FALSE()) -> REPARACION EN GENERAL | J4: 6923178 | K4: 57.6 | L4: =M4*K4/100*0.65 -> 7477032.2 | M4: =J4*1.05/(1-0.04-0.012-0.008-K4/100) -> 19970706 | N4: 19980631 | O4: PAGADO | P4: ARREGLOS EN GENERAL | Q4: 135 | R4: 132 | S4: NO | T4: NO APLICA | U4: 826 | V4: FACB0000200000325 | W4: 45804 | Z4: Aguardando
A5: AA-717-YI | B5: 322 | C5: 45665 | D5: 45680 | E5: 45692 | G5: 45692 | H5: =VLOOKUP($B5,PRESUPUESTOS!$A$4:$H$1026,3,FALSE()) -> ABSA - LINCONL | I5: =VLOOKUP($B5,PRESUPUESTOS!$A$4:$H$1026,5,FALSE()) -> VALVULA Y CODO GIRATORIO | J5: 1497426 | K5: 51 | L5: =M5*K5/100*0.65 -> 1212131.5 | M5: =J5*1.05/(1-0.04-0.012-0.008-K5/100) -> 3656505.3 | N5: 3687332 | O5: PAGADO | P5: CAMBIO DE CODO GIRATORIO Y VALVULAS | Q5: N/A | R5: N/A | S5: NO | T5: NO APLICA | U5: 4500025456 | V5: FACA0000300000036 | W5: 45721
A6: N/A | B6: 324 | C6: 45672 | D6: 45672 | E6: 45673 | G6: 45674 | H6: =VLOOKUP($B6,PRESUPUESTOS!$A$4:$H$1026,3,FALSE()) -> ADESSOTECH | I6: =VLOOKUP($B6,PRESUPUESTOS!$A$4:$H$1026,5,FALSE()) -> TOBERA ALUMINIO 1" | J6: 659465 | K6: 47.9 | L6: =M6*K6/100*0.65 -> 467658.67 | M6: =J6*1.05/(1-0.04-0.012-0.008-K6/100) -> 1502035.2 | N6: 1500333 | O6: PAGADO | P6: UNA TOBERA DE ALUMINIO DE 1" | Q6: N/A | R6: N/A | S6: NO | T6: NO APLICA | U6: 25 | V6: FACA0000200001362 | W6: 45674
A7: DSG-000 | B7: 326 | C7: 45686 | D7: 45691 | E7: 45692 | G7: 45748 | H7: =VLOOKUP($B7,PRESUPUESTOS!$A$4:$H$1026,3,FALSE()) -> SERVICIOS IBARRA | I7: =VLOOKUP($B7,PRESUPUESTOS!$A$4:$H$1026,5,FALSE()) -> TANQUE DE AGUA LADO CHOFER | J7: 3300000 | K7: 58.38 | L7: =M7*K7/100*0.65 -> 3691363.1 | M7: =J7*1.05/(1-0.04-0.012-0.008-K7/100) -> 9727681.1 | N7: 9580780 | O7: PAGADO | P7: TANQUE DE AGUA LADO CHOFER JET-VAC 4075 (50% anticipo - 50% contra entrega) | Q7: 18 | R7: 35 | S7: NO | T7: NO APLICA | U7: 2956 | V7: FACA0000200001367 | W7: 12/02/25 - 21/04/25
A8: AA-717-YI | B8: 327 | C8: 45698 | D8: 45730 | E8: 45736 | G8: 45807 | H8: =VLOOKUP($B8,PRESUPUESTOS!$A$4:$H$1026,3,FALSE()) -> ABSA - LINCONL | I8: =VLOOKUP($B8,PRESUPUESTOS!$A$4:$H$1026,5,FALSE()) -> TAPA DE TANQUE DESPERDICIO | J8: 6014400 | K8: 53.4 | L8: =M8*K8/100*0.65 -> 5398961 | M8: =J8*1.05/(1-0.04-0.012-0.008-K8/100) -> 15554483 | N8: 15584770 | O8: PAGADO | P8: FABRICACION DE TAPA TRASERA DE DESPERDICIO DE TANQUE - JET-VAC 4075 | Q8: 70 | R8: 83 | S8: SI | T8: FINALIZADA | U8: 4500026290 | V8: FACA0000300000041 | W8: 7/07/25 50%
A9: N/A | B9: 330 | C9: 45716 | D9: 45722 | E9: 45723 | G9: 45791 | H9: =VLOOKUP($B9,PRESUPUESTOS!$A$4:$H$1026,3,FALSE()) -> MUNICIPALIDAD DE JUNIN | I9: =VLOOKUP($B9,PRESUPUESTOS!$A$4:$H$1026,5,FALSE()) -> MANGUERA DESOBSTRUCTORA | J9: 2275951 | K9: 65.84 | L9: =M9*K9/100*0.65 -> 3631806.8 | M9: =J9*1.05/(1-0.04-0.012-0.008-K9/100) -> 8486323 | N9: 8482882 | O9: PAGADO | P9: MANGUERA DE 3/4 | Q9: N/A | R9: N/A | S9: NO | T9: NO APLICA | U9: 1799 | V9: FACB0000200000324 | W9: 45785
A10: KRD-066 | B10: 332 | C10: 45771 | D10: 45854 | E10: 45856 | F10: 45953 | G10: 45783 | H10: =VLOOKUP($B10,PRESUPUESTOS!$A$4:$H$1026,3,FALSE()) -> AGUAS RIONEGRINAS | I10: REPARACION EN GENERAL | J10: 19522313 | K10: 46 | L10: =M10*K10/100*0.65 -> 12768813 | M10: =J10*1.05/(1-0.04-0.012-0.008-K10/100) -> 42705060 | N10: 42776989 | O10: PAGADO | P10: ARREGLOS EN GENERAL AQUATECH | Q10: 88 | S10: NO | T10: NO APLICA | U10: 699 | V10: FACA0000200001397 | W10: 45968 | X10: 4605
A11: N/A | B11: 334 | C11: 45743 | D11: 45743 | E11: 45756 | G11: 45761 | H11: =VLOOKUP($B11,PRESUPUESTOS!$A$4:$H$1026,3,FALSE()) -> SAMSA | I11: =VLOOKUP($B11,PRESUPUESTOS!$A$4:$H$1026,5,FALSE()) -> TOBERAS | J11: 1448707 | K11: 37.87 | L11: =M11*K11/100*0.65 -> 667088.54 | M11: =J11*1.05/(1-0.04-0.012-0.008-K11/100) -> 2710034.5 | N11: 2710167 | O11: PAGADO | P11: TOBERAS VARIAS | Q11: N/A | R11: N/A | S11: NO | T11: NO APLICA | U11: 33043 | V11: FACA0000200001376 | W11: 45776
A12: AA-698-SW | B12: 344 | C12: 45763 | D12: 45817 | E12: 45834 | G12: 45764 | H12: =VLOOKUP($B12,PRESUPUESTOS!$A$4:$H$1026,3,FALSE()) -> ABSA -CAÑUELAS | I12: =VLOOKUP($B12,PRESUPUESTOS!$A$4:$H$1026,5,FALSE()) -> NOVEDADES | J12: 6224864 | K12: 44 | L12: =M12*K12/100*0.65 -> 3738653.3 | M12: =J12*1.05/(1-0.04-0.012-0.008-K12/100) -> 13072214 | N12: 13036296 | O12: PAGADO | P12: NOVEDADES REPARACION | Q12: 18 | R12: 29 | S12: NO | T12: NO APLICA | U12: 4500027506 | V12: FACA0000300000042 | W12: 45853
A13: N/A | B13: 345 | C13: 45767 | D13: 45768 | E13: 45769 | G13: 45769 | H13: =VLOOKUP($B13,PRESUPUESTOS!$A$4:$H$1026,3,FALSE()) -> INDUMAT | I13: =VLOOKUP($B13,PRESUPUESTOS!$A$4:$H$1026,5,FALSE()) -> BURLETE | J13: 268620 | K13: 35.3 | L13: =M13*K13/100*0.65 -> 110249.75 | M13: =J13*1.05/(1-0.04-0.012-0.008-K13/100) -> 480495.74 | N13: 480078.39 | O13: ESPERANDO PAGO | P13: BURLETE PLUMA A TANQUE | Q13: N/A | R13: N/A | S13: NO | T13: NO APLICA | U13: 2330 | V13: FACA0000200001377
A14: JZH-095 | B14: 347 | C14: 45772 | D14: 45772 | E14: 45775 | G14: 45783 | H14: =VLOOKUP($B14,PRESUPUESTOS!$A$4:$H$1026,3,FALSE()) -> MUNICIPALIDAD SANTA ROSA | I14: =VLOOKUP($B14,PRESUPUESTOS!$A$4:$H$1026,5,FALSE()) -> SERVICIOS DE TRASLADO | J14: 3388000 | K14: 10 | L14: =M14*K14/100*0.65 -> 275275 | M14: =J14*1.05/(1-0.04-0.012-0.008-K14/100) -> 4235000 | N14: 4235000 | O14: PAGADO | P14: TRASLADO DE EQUIPO A PLANTA OCME | Q14: N/A | R14: N/A | S14: NO | T14: NO APLICA | U14: 487 | V14: FACA0000200001378 | W14: 45835
A15: AA-717-YM | B15: 348 | C15: 45782 | D15: 45834 | E15: 45854 | G15: 45854 | H15: =VLOOKUP($B15,PRESUPUESTOS!$A$4:$H$1026,3,FALSE()) -> ABSA LA PLATA | I15: =VLOOKUP($B15,PRESUPUESTOS!$A$4:$H$1026,5,FALSE()) -> BLOWER | J15: 22911160 | K15: 37.3 | L15: =M15*K15/100*0.65 -> 10286687 | M15: =J15*1.05/(1-0.04-0.012-0.008-K15/100) -> 42428074 | N15: 42411468 | O15: PAGADO | P15: REMPLAZO DE BLOWER | Q15: 18 | R15: 16 | S15: NO | T15: NO APLICA | U15: 4500027607 | V15: FACA0000200001396 | W15: 45918
A16: AB-949-NT | B16: 349 | C16: 45804 | D16: 45812 | E16: 5/06/25 - | G16: 45898 | H16: =VLOOKUP($B16,PRESUPUESTOS!$A$4:$H$1026,3,FALSE()) -> MUNICIPALIDAD DE JUNIN | I16: =VLOOKUP($B16,PRESUPUESTOS!$A$4:$H$1026,5,FALSE()) -> REPARACION EN GENERAL | J16: 9837346 | K16: 68.8 | L16: =M16*K16/100*0.65 -> 18330255 | M16: =J16*1.05/(1-0.04-0.012-0.008-K16/100) -> 40988942 | N16: 41103821 | O16: PAGADO | P16: REPARACION EN GENERAL JET-VAC 4500-D | Q16: 240 | R16: 230 | S16: NO | T16: NO APLICA | U16: 5058 | V16: FACB0000200000326 - FACB0000200000335 | W16: 29/08/25 - 25/09/25
A17: JZH-095 | B17: 350 | C17: 45792 | D17: 45797 | E17: 45798 | G17: 45944 | H17: =VLOOKUP($B17,PRESUPUESTOS!$A$4:$H$1026,3,FALSE()) -> MUNICIPALIDAD SANTA ROSA | I17: =VLOOKUP($B17,PRESUPUESTOS!$A$4:$H$1026,5,FALSE()) -> REPARACION EN CAJA DE TRANSFERENCIA | J17: 17473866 | K17: 39.5 | L17: =M17*K17/100*0.65 -> 8643552 | M17: =J17*1.05/(1-0.04-0.012-0.008-K17/100) -> 33665246 | N17: 35368993 | O17: PAGADO | P17: ADAPTACION CAJA DE TRANSFERENCIA | Q17: 80 | R17: 98 | S17: SI | T17: FINALIZADA 5/12/25 | U17: 558 | V17: FACA0000200001383 | W17: 45944 | X17: 4604
A18: HEZ-261 | B18: 290 | C18: 45750 | D18: 45796 | E18: 19/05/25 - | H18: =VLOOKUP($B18,PRESUPUESTOS!$A$4:$H$1026,3,FALSE()) -> ABSA - LAS FLORES | I18: =VLOOKUP($B18,PRESUPUESTOS!$A$4:$H$1026,5,FALSE()) -> INSPECCION DE ARREGLOS EN GENERAL | J18: 15133940 | K18: 47.4 | L18: =M18*K18/100*0.65 -> 10506234 | M18: =J18*1.05/(1-0.04-0.012-0.008-K18/100) -> 34100079 | N18: 34101996 | O18: 0.5 | P18: ADAPTACION BOMBA DE AGUA A EQUIPO HIDRO SCORZA | Q18: 131 | S18: SI | T18: VIGENTE | U18: 4500026873 | V18: FACA0000300000040
A19: N/A | B19: 352 | C19: 45792 | D19: 45793 | E19: 45818 | G19: 45818 | H19: =VLOOKUP($B19,PRESUPUESTOS!$A$4:$H$1026,3,FALSE()) -> AUTOMAT | I19: =VLOOKUP($B19,PRESUPUESTOS!$A$4:$H$1026,5,FALSE()) -> ARENADO DE VIGAS | J19: 8000000 | K19: 47.7 | L19: =M19*K19/100*0.65 -> 5625097.2 | M19: =J19*1.05/(1-0.04-0.012-0.008-K19/100) -> 18142549 | N19: 18150000 | O19: PAGADO | P19: SERVICIO DE ARENADO MALDONADO | Q19: N/A | R19: N/A | S19: NO | T19: NO APLICA | U19: no enviaron | V19: FACA0000200001388
A20: AA-717-YL | B20: 355 | C20: 45803 | D20: 45869 | E20: 45869 | G20: 45803 | H20: =VLOOKUP($B20,PRESUPUESTOS!$A$4:$H$1026,3,FALSE()) -> ABSA - LA PLATA | I20: =VLOOKUP($B20,PRESUPUESTOS!$A$4:$H$1026,5,FALSE()) -> NOVEDADES | J20: 2923633 | K20: 62 | L20: =M20*K20/100*0.65 -> 3866047.8 | M20: =J20*1.05/(1-0.04-0.012-0.008-K20/100) -> 9593170.8 | N20: 9634719.3 | O20: PAGADO | P20: NOVEDADES DE REPARACION (problema con el pago, se re FC) | Q20: 89 | R20: 80 | S20: NO | T20: NO APLICA | U20: 4500028490 | V20: FACA0000200001399 | W20: 45918
A21: AA-717-YI | B21: 356 | C21: 45807 | D21: 45841 | E21: 45842 | G21: 45807 | H21: =VLOOKUP($B21,PRESUPUESTOS!$A$4:$H$1026,3,FALSE()) -> ABSA - LINCOLN | I21: =VLOOKUP($B21,PRESUPUESTOS!$A$4:$H$1026,5,FALSE()) -> NOVEDADES | J21: 4382887 | K21: 47 | L21: =M21*K21/100*0.65 -> 2991320.4 | M21: =J21*1.05/(1-0.04-0.012-0.008-K21/100) -> 9791556.1 | N21: 9778860.3 | O21: PAGADO | P21: NOVEDADES TAPA DE TANQUE, ITEMS ITERNOS | Q21: 18 | R21: 16 | S21: NO | T21: NO APLICA | U21: 4500027761 | V21: FACA0000200001395 | W21: 45855
A22: DAT-754 | B22: 358 | C22: 45806 | D22: 45860 | E22: 45866 | G22: 45925 | H22: =VLOOKUP($B22,PRESUPUESTOS!$A$4:$H$1026,3,FALSE()) -> MUNICIPALIDAD TRES ARROYOS | I22: AGREGADOS | J22: 3283452 | K22: 68 | L22: =M22*K22/100*0.65 -> 5860961.8 | M22: =J22*1.05/(1-0.04-0.012-0.008-K22/100) -> 13260095 | N22: 13472938 | O22: PAGADO | P22: AGREGADOS Y NOVEDADES | Q22: 57 | R22: 58 | S22: NO | T22: NO APLICA | U22: 3035 | V22: FACB0000200000332 | W22: 45925
A23: MAN | B23: 364 | C23: 45820 | D23: 45846 | E23: 45846 | G23: 45877 | H23: =VLOOKUP($B23,PRESUPUESTOS!$A$4:$H$1026,3,FALSE()) -> MUNICIPALIDAD TRES ARROYOS | I23: =VLOOKUP($B23,PRESUPUESTOS!$A$4:$H$1026,5,FALSE()) -> MANGUERA DESOBSTRUCTORA 1" | J23: 4481244 | K23: 28 | L23: =M23*K23/100*0.65 -> 1297523.8 | M23: =J23*1.05/(1-0.04-0.012-0.008-K23/100) -> 7129251.8 | N23: 7160000 | O23: PAGADO | P23: MANGUERA DESOBSTRUCTORA DE 1" MARCA ZEC 152 MTS | Q23: N/A | R23: N/A | S23: NO | T23: NO APLICA | U23: 2938 | V23: FACB0000200000327 | W23: 45877
A24: HEZ-261 | B24: 367 | C24: 45841 | D24: 45939 | E24: 45971 | H24: =VLOOKUP($B24,PRESUPUESTOS!$A$4:$H$1026,3,FALSE()) -> ABSA - LAS FLORES | I24: =VLOOKUP($B24,PRESUPUESTOS!$A$4:$H$1026,5,FALSE()) -> AGREGADOS Y NOVEDADES | J24: 7000000 | K24: 57.4 | L24: =M24*K24/100*0.65 -> 7492582 | M24: =J24*1.05/(1-0.04-0.012-0.008-K24/100) -> 20081967 | N24: 20104860 | O24: ESPERANDO PAGO | P24: AGEGADOS Y NOVEDADES SUJETA A COTIZACION Nº290 | Q24: 65 | S24: SI | T24: VIGENTE | U24: 4500029647 | V24: FACA0000200001430
A25: AA-717-YI | B25: 368 | C25: 45833 | D25: 45862 | E25: 45869 | G25: 45835 | H25: =VLOOKUP($B25,PRESUPUESTOS!$A$4:$H$1026,3,FALSE()) -> ABSA - LINCOLN | I25: =VLOOKUP($B25,PRESUPUESTOS!$A$4:$H$1026,5,FALSE()) -> CABLE DE ACELERADOR | J25: 381150 | K25: 53.5 | L25: =M25*K25/100*0.65 -> 343634.96 | M25: =J25*1.05/(1-0.04-0.012-0.008-K25/100) -> 988166.67 | N25: 988267 | O25: PAGADO | P25: CABLE ACELERADOR BOMBA DE AGUA | Q25: N/A | R25: N/A | S25: NO | T25: NO APLICA | U25: 4500028299 | V25: FACA0000200001400 | W25: 45918
A26: N/A | B26: 369 | C26: 45842 | D26: 45853 | E26: 45856 | G26: 45868 | H26: =VLOOKUP($B26,PRESUPUESTOS!$A$4:$H$1026,3,FALSE()) -> MUNICIPALIDAD SANTA TERESITA | I26: =VLOOKUP($B26,PRESUPUESTOS!$A$4:$H$1026,5,FALSE()) -> TOBERAS | J26: 1068983 | K26: 30 | L26: =M26*K26/100*0.65 -> 341991.05 | M26: =J26*1.05/(1-0.04-0.012-0.008-K26/100) -> 1753800.2 | N26: 1748371.4 | O26: PAGADO | P26: TOBERAS VARIAS EN 1" | Q26: N/A | R26: N/A | S26: NO | T26: NO APLICA | U26: 20250004 | V26: FACA0000200001398 | W26: 45862
A27: AB-949-NT | B27: 371 | C27: 45846 | D27: 45849 | E27: 45852 | G27: 45898 | H27: =VLOOKUP($B27,PRESUPUESTOS!$A$4:$H$1026,3,FALSE()) -> MUNICIPALIDAD DE JUNIN | I27: =VLOOKUP($B27,PRESUPUESTOS!$A$4:$H$1026,5,FALSE()) -> KIT DE REPARACION BOMBA DE AGUA | J27: 2842497 | K27: 32 | L27: =M27*K27/100*0.65 -> 1001292.5 | M27: =J27*1.05/(1-0.04-0.012-0.008-K27/100) -> 4813906.2 | N27: 4783502.7 | O27: PAGADO | P27: REPUESTOS KIT BOMBA KF36 | Q27: N/A | R27: N/A | S27: NO | T27: NO APLICA | U27: 6526 | V27: FACB0000200000329 | W27: 13025
A28: LWV-091 | B28: 372 | C28: 45855 | D28: 45859 | E28: 45859 | G28: 45898 | H28: =VLOOKUP($B28,PRESUPUESTOS!$A$4:$H$1026,3,FALSE()) -> MUNICIPALIDAD DE JUNIN | I28: =VLOOKUP($B28,PRESUPUESTOS!$A$4:$H$1026,5,FALSE()) -> TOBERAS VARIAS 1" | J28: 2207900 | K28: 34 | L28: =M28*K28/100*0.65 -> 853905.33 | M28: =J28*1.05/(1-0.04-0.012-0.008-K28/100) -> 3863825 | N28: 3795836.5 | O28: PAGADO | P28: TOBERAS DE 1" VARIAS | Q28: N/A | R28: N/A | S28: NO | T28: NO APLICA | U28: 6944 | V28: FACB0000200000330 | W28: 13025
A29: AA-717-YL | B29: 378 | C29: 45868 | D29: 45926 | E29: 45946 | F29: 45987 | G29: 45953 | H29: =VLOOKUP($B29,PRESUPUESTOS!$A$4:$H$1026,3,FALSE()) -> ABSA - LA PLATA | I29: =VLOOKUP($B29,PRESUPUESTOS!$A$4:$H$1026,5,FALSE()) -> DESARME Y DIAGNOSTICO | J29: 370000 | K29: 46 | L29: =M29*K29/100*0.65 -> 242003.13 | M29: =J29*1.05/(1-0.04-0.012-0.008-K29/100) -> 809375 | N29: 807520.12 | O29: PAGADO | P29: DESARME Y DIAGNOSTICO | Q29: 15 | R29: 15 | S29: NO | T29: NO APLICA | U29: 4500029404 | V29: FACA0000200001420
A30: LWV-091 | B30: 382 | C30: 45877 | D30: 45881 | E30: 45881 | G30: 45957 | H30: =VLOOKUP($B30,PRESUPUESTOS!$A$4:$H$1026,3,FALSE()) -> MUNICIPALIDAD DE JUNIN | I30: =VLOOKUP($B30,PRESUPUESTOS!$A$4:$H$1026,5,FALSE()) -> TERMINALES PARA MANGUERA DE AGUA | J30: 700106 | K30: 34 | L30: =M30*K30/100*0.65 -> 270766 | M30: =J30*1.05/(1-0.04-0.012-0.008-K30/100) -> 1225185.5 | N30: 1223121.2 | O30: PAGADO | P30: TERMINALES PARA MANGUERA DE AGUA | Q30: N/A | R30: N/A | S30: NO | T30: NO APLICA | U30: 7769 | V30: FACB0000200000334 | W30: 45957 | X30: 4606
A31: N/A | B31: 384 | C31: 45889 | D31: 45889 | E31: 45897 | G31: 45909 | H31: =VLOOKUP($B31,PRESUPUESTOS!$A$4:$H$1026,3,FALSE()) -> ASHIRA | I31: =VLOOKUP($B31,PRESUPUESTOS!$A$4:$H$1026,5,FALSE()) -> TOBERAS | J31: 1487749 | K31: 35 | L31: =M31*K31/100*0.65 -> 602349.22 | M31: =J31*1.05/(1-0.04-0.012-0.008-K31/100) -> 2647688.9 | N31: 2640027.6 | O31: PAGADO | P31: TOBERA SAPO GRANDE 1" , OVOIDAL DE 1" | Q31: N/A | R31: N/A | S31: NO | T31: NO APLICA | U31: 00098-0000002987 | V31: FACA0000200001406 | W31: 45909
A32: N/A | B32: 399 | C32: 45943 | D32: 45945 | E32: 45957 | G32: 45914 | H32: =VLOOKUP($B32,PRESUPUESTOS!$A$4:$H$1026,3,FALSE()) -> MUNICIPALIDAD SANTA ROSA | I32: =VLOOKUP($B32,PRESUPUESTOS!$A$4:$H$1026,5,FALSE()) -> BATERIA | J32: 306600 | K32: 13 | L32: =M32*K32/100*0.65 -> 33584.056 | M32: =J32*1.05/(1-0.04-0.012-0.008-K32/100) -> 397444.44 | N32: 394763 | O32: ESPERANDO PAGO | P32: TOBERA MOURA 12X180 | Q32: N/A | R32: N/A | S32: NO | T32: NO APLICA | U32: 1139 | V32: FACA0000200001421 | W32: 45944 | X32: 4604
A33: KRD-066 | B33: 404 | C33: 45967 | H33: =VLOOKUP($B33,PRESUPUESTOS!$A$4:$H$1026,3,FALSE()) -> AGUAS RIONEGRINAS | I33: =VLOOKUP($B33,PRESUPUESTOS!$A$4:$H$1026,5,FALSE()) -> NOVEDADES | J33: 2161250 | K33: 30 | L33: =M33*K33/100*0.65 -> 691431.15 | M33: =J33*1.05/(1-0.04-0.012-0.008-K33/100) -> 3545800.8 | O33: ESPERANDO OC | P33: DIAGNOSTICO, DESARME Y CAMBIO DE INYECTOR Nº2 | Q33: 25 | R33: 25 | S33: NO | T33: NO APLICA | X33: 4605
A34: DSG-000 | B34: 407 | C34: 45966 | D34: 45967 | E34: 45967 | F34: 45967 | G34: 45967 | H34: =VLOOKUP($B34,PRESUPUESTOS!$A$4:$H$1026,3,FALSE()) -> SERVICIOS IBARRA | I34: =VLOOKUP($B34,PRESUPUESTOS!$A$4:$H$1026,5,FALSE()) -> BURLETES | J34: 200000 | K34: 65 | L34: =M34*K34/100*0.65 -> 305948.28 | M34: =J34*1.05/(1-0.04-0.012-0.008-K34/100) -> 724137.93 | N34: 724608 | O34: PAGADO | P34: BURLETE DE PLUMA JET-VAC 4075 ARMADO | Q34: N/A | R34: N/A | S34: NO | T34: NO APLICA | U34: No enviaron | V34: FACA0000200001429 | W34: 45967 | X34: 4607
A35: N/A | B35: 410 | C35: 45990 | D35: 45992 | E35: 45992 | H35: =VLOOKUP($B35,PRESUPUESTOS!$A$4:$H$1026,3,FALSE()) -> COSERCO CORONDA | I35: =VLOOKUP($B35,PRESUPUESTOS!$A$4:$H$1026,5,FALSE()) -> MANGUERA 3/4" | K35: 65 | L35: =M35*K35/100*0.65 -> 0 | M35: =J35*1.05/(1-0.04-0.012-0.008-K35/100) -> 0 | N35: 4283400 | O35: ESPERANDO PAGO | P35: MANGUERA DESOBSTRUCTORA DE 3/4" PREDATOR PARKER 150 MTS | Q35: N/A | R35: N/A | S35: NO | T35: NO APLICA | U35: 9614 | V35: FACA0000200001437
H36: =VLOOKUP($B36,PRESUPUESTOS!$A$4:$H$1026,3,FALSE()) -> #N/A | I36: =VLOOKUP($B36,PRESUPUESTOS!$A$4:$H$1026,5,FALSE()) -> #N/A
H37: =VLOOKUP($B37,PRESUPUESTOS!$A$4:$H$1026,3,FALSE()) -> #N/A | I37: =VLOOKUP($B37,PRESUPUESTOS!$A$4:$H$1026,5,FALSE()) -> #N/A
H38: =VLOOKUP($B38,PRESUPUESTOS!$A$4:$H$1026,3,FALSE()) -> #N/A | I38: =VLOOKUP($B38,PRESUPUESTOS!$A$4:$H$1026,5,FALSE()) -> #N/A
H39: =VLOOKUP($B39,PRESUPUESTOS!$A$4:$H$1026,3,FALSE()) -> #N/A | I39: =VLOOKUP($B39,PRESUPUESTOS!$A$4:$H$1026,5,FALSE()) -> #N/A
H40: =VLOOKUP($B40,PRESUPUESTOS!$A$4:$H$1026,3,FALSE()) -> #N/A | I40: =VLOOKUP($B40,PRESUPUESTOS!$A$4:$H$1026,5,FALSE()) -> #N/A
H41: =VLOOKUP($B41,PRESUPUESTOS!$A$4:$H$1026,3,FALSE()) -> #N/A | I41: =VLOOKUP($B41,PRESUPUESTOS!$A$4:$H$1026,5,FALSE()) -> #N/A
H42: =VLOOKUP($B42,PRESUPUESTOS!$A$4:$H$1026,3,FALSE()) -> #N/A | I42: =VLOOKUP($B42,PRESUPUESTOS!$A$4:$H$1026,5,FALSE()) -> #N/A
H43: =VLOOKUP($B43,PRESUPUESTOS!$A$4:$H$1026,3,FALSE()) -> #N/A | I43: =VLOOKUP($B43,PRESUPUESTOS!$A$4:$H$1026,5,FALSE()) -> #N/A
H44: =VLOOKUP($B44,PRESUPUESTOS!$A$4:$H$1026,3,FALSE()) -> #N/A | I44: =VLOOKUP($B44,PRESUPUESTOS!$A$4:$H$1026,5,FALSE()) -> #N/A
H45: =VLOOKUP($B45,PRESUPUESTOS!$A$4:$H$1026,3,FALSE()) -> #N/A | I45: =VLOOKUP($B45,PRESUPUESTOS!$A$4:$H$1026,5,FALSE()) -> #N/A
H46: =VLOOKUP($B46,PRESUPUESTOS!$A$4:$H$1026,3,FALSE()) -> #N/A | I46: =VLOOKUP($B46,PRESUPUESTOS!$A$4:$H$1026,5,FALSE()) -> #N/A
H47: =VLOOKUP($B47,PRESUPUESTOS!$A$4:$H$1026,3,FALSE()) -> #N/A | I47: =VLOOKUP($B47,PRESUPUESTOS!$A$4:$H$1026,5,FALSE()) -> #N/A
... H70: =VLOOKUP($B70,PRESUPUESTOS!$A$4:$H$1026,3,FALSE()) -> #N/A | I70: =VLOOKUP($B70,PRESUPUESTOS!$A$4:$H$1026,5,FALSE()) -> #N/A

Sheet HISTORICO
A1: Nº | B1: CLIENTE | C1: DESCRIPCION | D1: FECHA INICIO | E1: COSTO | F1: A COBRAR | G1: GANANCIA | H1: ESTADO | I1: FECHA FINALIZACION | K1: HS COTIZADAS | L1: HS UTILIZADAS | M1: STOCK
A2: 230 | B2: =VLOOKUP($A2,PRESUPUESTOS!$A$4:$H$1026,3,FALSE()) -> TRES ARROYOS | C2: =VLOOKUP($A2,PRESUPUESTOS!$A$4:$H$1026,5,FALSE()) -> MANGUERA DESOBSTRUCTORA | D2: 45338 | F2: 6006056 | G2: 6006056 | H2: PAGADO | I2: 45365 | J2: PAGADO, FINALIZADO. | K2: N/A | L2: N/A
A3: 238 | B3: =VLOOKUP($A3,PRESUPUESTOS!$A$4:$H$1026,3,FALSE()) -> ABSA - LA PLATA | C3: =VLOOKUP($A3,PRESUPUESTOS!$A$4:$H$1026,5,FALSE()) -> 0 | D3: 45313 | F3: 13796755 | H3: PAGADO | I3: 45462 | J3: REPARACIONES EN GENERAL | K3: 125
A4: 249 | B4: =VLOOKUP($A4,PRESUPUESTOS!$A$4:$H$1026,3,FALSE()) -> ABSA - REGION 5 | C4: =VLOOKUP($A4,PRESUPUESTOS!$A$4:$H$1026,5,FALSE()) -> ARREGLO EN GENERAL, EN REPARACION | D4: 45453 | E4: 8038384 | F4: 15923950 | G4: =F4-E4 -> 7885565.8 | H4: PAGADO | I4: 45705 | J4: ARREGLO EN GENERAL MAS AGREGADOS | K4: 123
A5: 258 | B5: =VLOOKUP($A5,PRESUPUESTOS!$A$4:$H$1026,3,FALSE()) -> ABSA - LINCOLN | C5: =VLOOKUP($A5,PRESUPUESTOS!$A$4:$H$1026,5,FALSE()) -> ARREGLOS EN GENERAL | D5: 45427 | E5: 7511257 | F5: 25088834 | G5: =F5-E5 -> 17577578 | H5: PAGADO | I5: 45600 | J5: REPARACIONES EN GENERAL | K5: 123 | L5: 228.5
A6: 263 | B6: =VLOOKUP($A6,PRESUPUESTOS!$A$4:$H$1026,3,FALSE()) -> SERVICIOS IBARRA | C6: =VLOOKUP($A6,PRESUPUESTOS!$A$4:$H$1026,5,FALSE()) -> REJA CANASTO Y BOYA | D6: 45435 | F6: 800000 | G6: =F6-E6 -> 800000 | H6: PAGADO | I6: 45443 | J6: REJA CANASTO Y BOYA | K6: N/A | L6: N/A | M6: SIN ROPONER
A7: 271 | B7: =VLOOKUP($A7,PRESUPUESTOS!$A$4:$H$1026,3,FALSE()) -> ABSA - LA PLATA | C7: =VLOOKUP($A7,PRESUPUESTOS!$A$4:$H$1026,5,FALSE()) -> TERCERIZADO FORD CIRCUITO DE COMBUSTIBLE | D7: 45456 | E7: 1682944 | F7: 2395800 | G7: =F7-E7 -> 712856 | H7: PAGADO | I7: 45600 | J7: TERCERIZADO FORD CIRCUITO DE COMBUSTIBLE | K7: N/A | L7: N/A
A8: 276 | B8: =VLOOKUP($A8,PRESUPUESTOS!$A$4:$H$1026,3,FALSE()) -> ABSA - CAÑUELAS | C8: =VLOOKUP($A8,PRESUPUESTOS!$A$4:$H$1026,5,FALSE()) -> SOPLADOR REPYCKY R3.8 (BLOWER) | D8: 45573 | E8: 20072161 | F8: 34449608 | G8: =F8-E8 -> 14377447 | H8: PAGADO | I8: 45590 | J8: CAMBIO DE BLOWER PARA AA-698-SW, NO SE PUEDE REPARAR Y SE AVANZA POR UNO NUEVO | K8: N/A | L8: N/A
A9: 279 | B9: =VLOOKUP($A9,PRESUPUESTOS!$A$4:$H$1026,3,FALSE()) -> AGUAS RIONEGRINAS | C9: =VLOOKUP($A9,PRESUPUESTOS!$A$4:$H$1026,5,FALSE()) -> ENGRANAJES DE CAJA COTTA | D9: 45496 | E9: 6661700 | F9: 22834030 | G9: =F9-E9 -> 16172330 | H9: PAGADO | I9: 45525 | J9: ENGRANAJES | K9: N/A | L9: N/A | M9: SIN ROPONER
A10: 280 | B10: =VLOOKUP($A10,PRESUPUESTOS!$A$4:$H$1026,3,FALSE()) -> M. JUNIN | C10: =VLOOKUP($A10,PRESUPUESTOS!$A$4:$H$1026,5,FALSE()) -> MANGUERA DESOBSTRUCTORA 1" | D10: 45499 | E10: 5718774 | F10: 9382364 | G10: =F10-E10 -> 3663590 | H10: PAGADO | I10: 45523 | J10: MANGUERA DESOBSTRUCTORA 1" | K10: N/A | L10: N/A
A11: 281 | B11: =VLOOKUP($A11,PRESUPUESTOS!$A$4:$H$1026,3,FALSE()) -> OSSE | C11: =VLOOKUP($A11,PRESUPUESTOS!$A$4:$H$1026,5,FALSE()) -> BURLETE DE SELLO DE TANQUE | D11: 45505 | E11: 235950 | F11: 805134 | G11: =F11-E11 -> 569184 | H11: PAGADO | I11: 45566 | J11: BURLETE DE SELLO DE TANQUE 4075 | K11: N/A | L11: N/A | M11: SIN ROPONER
A12: 287 | B12: =VLOOKUP($A12,PRESUPUESTOS!$A$4:$H$1026,3,FALSE()) -> M.JUNIN | C12: =VLOOKUP($A12,PRESUPUESTOS!$A$4:$H$1026,5,FALSE()) -> FILTRO ACERO INOXIDABLE, RETENCION 200 MICRONES DE 70 H: 138MM ESTAÑADO, VALVULA DESVIAORA | D12: 45513 | E12: 507671 | F12: 1642817 | G12: =F12-E12 -> 1135146 | H12: PAGADO | I12: 45534 | J12: FILTRO ACERO INOXIDABLE, RETENCION 200 MICRONES DE 70 H: 138MM ESTAÑADO, VALVULA DESVIAORA | K12: N/A | L12: N/A
A13: 288 | B13: =VLOOKUP($A13,PRESUPUESTOS!$A$4:$H$1026,3,FALSE()) -> AGUAS RIONEGRINAS | C13: =VLOOKUP($A13,PRESUPUESTOS!$A$4:$H$1026,5,FALSE()) -> EMBRAGUE CAJA COTA | D13: 45518 | E13: 1888103 | F13: 5558268 | G13: =F13-E13 -> 3670165 | H13: PAGADO | I13: 45544 | J13: EMBRAGUE CAJA COTA | K13: N/A | L13: N/A | M13: SIN ROPONER
A14: 255 | B14: =VLOOKUP($A14,PRESUPUESTOS!$A$4:$H$1026,3,FALSE()) -> ABSA | C14: =VLOOKUP($A14,PRESUPUESTOS!$A$4:$H$1026,5,FALSE()) -> ACARREO Y INSPECCION DE CAMIONES DE ABSA (AA-717-YL, AA-717-YM) | D14: 45511 | E14: 750200 | F14: 1064800 | G14: =F14-E14 -> 314600 | H14: PAGADO | I14: 45582 | J14: REMOLQUES DE CAMIONES PARA REPARACION EN TALLER | K14: N/A | L14: N/A
A15: 293 | B15: =VLOOKUP($A15,PRESUPUESTOS!$A$4:$H$1026,3,FALSE()) -> M.JUNIN | C15: =VLOOKUP($A15,PRESUPUESTOS!$A$4:$H$1026,5,FALSE()) -> TOBERAS, GRANADA OVOIDAL 3/4 | D15: 45531 | E15: 594160.02 | F15: 1417659 | G15: =F15-E15 -> 823498.97 | H15: PAGADO | I15: 45551 | J15: 2 TOBERAS DE 3/4 GRANADA Y 1 OVOIDAL DE 3/4 | K15: N/A | L15: N/A
A16: 291 | B16: =VLOOKUP($A16,PRESUPUESTOS!$A$4:$H$1026,3,FALSE()) -> M.JUNIN | C16: =VLOOKUP($A16,PRESUPUESTOS!$A$4:$H$1026,5,FALSE()) -> INSPECCION Y ARREGLOS EN GENERAL | D16: 45559 | E16: 14384301 | F16: 40541774 | G16: =F16-E16 -> 26157473 | H16: PAGADO | I16: 45603 | J16: ARREGLOS EN GENERAL | K16: 302
A17: 294 | B17: =VLOOKUP($A17,PRESUPUESTOS!$A$4:$H$1026,3,FALSE()) -> M.BERAZATEGUI | C17: =VLOOKUP($A17,PRESUPUESTOS!$A$4:$H$1026,5,FALSE()) -> REPARACION BOMBA DE AGUA | D17: 45574 | E17: 372315 | F17: 1424151 | G17: =F17-E17 -> 1051836 | H17: PAGADO | I17: 45579 | J17: REPARACION EQUIPO VACTOR 2100 BOMBA RODER | K17: 6 | L17: 5
A18: 301 | B18: =VLOOKUP($A18,PRESUPUESTOS!$A$4:$H$1026,3,FALSE()) -> ABSA-CAÑUELAS | C18: =VLOOKUP($A18,PRESUPUESTOS!$A$4:$H$1026,5,FALSE()) -> CILINDRO DE TANQUE | D18: 45635 | E18: 3468607 | F18: 6551015 | G18: =F18-E18 -> 3082408 | H18: PAGADO | I18: 45656 | J18: CILINDRO DE TANQUE | K18: N/A | L18: N/A
A19: 310 | B19: =VLOOKUP($A19,PRESUPUESTOS!$A$4:$H$1026,3,FALSE()) -> ABSA - LA PLATA | C19: =VLOOKUP($A19,PRESUPUESTOS!$A$4:$H$1026,5,FALSE()) -> ARREGLOS EN GENERAL | D19: 45664 | E19: 5136802 | F19: 22243813 | G19: =F19-E19 -> 17107011 | H19: PAGADO | J19: ARREGLOS EN GENERAL
A20: 313 | B20: =VLOOKUP($A20,PRESUPUESTOS!$A$4:$H$1026,3,FALSE()) -> SCPL | C20: =VLOOKUP($A20,PRESUPUESTOS!$A$4:$H$1026,5,FALSE()) -> TOBERAS Y ABRAZADERAS | D20: 45604 | E20: 5388026 | F20: 9869493 | G20: =F20-E20 -> 4481467 | H20: PAGADO | I20: 45618 | J20: TOBERAS Y ABRAZADERAS | K20: N/A | L20: N/A
A21: 314 | B21: =VLOOKUP($A21,PRESUPUESTOS!$A$4:$H$1026,3,FALSE()) -> M.BERAZATEGUI | C21: =VLOOKUP($A21,PRESUPUESTOS!$A$4:$H$1026,5,FALSE()) -> REPARACION DE BOMBA RODER | D21: 45618 | E21: 830457 | F21: 3870363 | G21: =F21-E21 -> 3039906 | H21: PAGADO | I21: 45630 | J21: CAMBIO DE SELLOS Y FABRICACION DE VARILLA ($812.776) | K21: 30
A22: 315 | B22: =VLOOKUP($A22,PRESUPUESTOS!$A$4:$H$1026,3,FALSE()) -> ABSA - LA PLATA | C22: =VLOOKUP($A22,PRESUPUESTOS!$A$4:$H$1026,5,FALSE()) -> REPARACION EN GENERAL | D22: 45664 | E22: 3898795 | F22: 18883614 | G22: =F22-E22 -> 14984819 | H22: PAGADO | J22: ARREGLOS EN GENERAL
A23: 317 | B23: =VLOOKUP($A23,PRESUPUESTOS!$A$4:$H$1026,3,FALSE()) -> MUNICIPALIDAD TRES ARROYOS | C23: =VLOOKUP($A23,PRESUPUESTOS!$A$4:$H$1026,5,FALSE()) -> REPARACION EN GENERAL | D23: 45701 | E23: 6923178 | F23: 19980631 | G23: =F23-E23 -> 13057453 | H23: PAGADO | J23: ARREGLOS EN GENERAL
A24: 322 | B24: =VLOOKUP($A24,PRESUPUESTOS!$A$4:$H$1026,3,FALSE()) -> ABSA - LINCONL | C24: =VLOOKUP($A24,PRESUPUESTOS!$A$4:$H$1026,5,FALSE()) -> VALVULA Y CODO GIRATORIO | D24: 45692 | E24: 1497426 | F24: 3687332 | G24: =F24-E24 -> 2189906 | H24: PAGADO | J24: CAMBIO DE CODO GIRATORIO Y VALVULAS
A25: 324 | B25: =VLOOKUP($A25,PRESUPUESTOS!$A$4:$H$1026,3,FALSE()) -> ADESSOTECH | C25: =VLOOKUP($A25,PRESUPUESTOS!$A$4:$H$1026,5,FALSE()) -> TOBERA ALUMINIO 1" | D25: 45672 | E25: 659465 | F25: 1500333 | G25: =F25-E25 -> 840868 | H25: PAGADO | I25: 45674 | J25: UNA TOBERA DE ALUMINIO DE 1" | K25: N/A | L25: N/A | M25: SIN REPONER
A26: 326 | B26: =VLOOKUP($A26,PRESUPUESTOS!$A$4:$H$1026,3,FALSE()) -> SERVICIOS IBARRA | C26: =VLOOKUP($A26,PRESUPUESTOS!$A$4:$H$1026,5,FALSE()) -> TANQUE DE AGUA LADO CHOFER | D26: 45692 | E26: 3248850 | F26: 9580780 | G26: =F26-E26 -> 6331930 | H26: PAGADO | I26: 12/02/25 - | J26: TANQUE DE AGUA LADO CHOFER JET-VAC 4075 (50% anticipo - 50% contra entrega)
A27: 327 | B27: =VLOOKUP($A27,PRESUPUESTOS!$A$4:$H$1026,3,FALSE()) -> ABSA - LINCONL | C27: =VLOOKUP($A27,PRESUPUESTOS!$A$4:$H$1026,5,FALSE()) -> TAPA DE TANQUE DESPERDICIO | D27: 45698 | E27: 6014400 | F27: 15584770 | G27: =F27-E27 -> 9570370 | H27: PAGADO | J27: FABRICACION DE TAPA TRASERA DE DESPERDICIO DE TANQUE - JET-VAC 4075
A28: 330 | B28: =VLOOKUP($A28,PRESUPUESTOS!$A$4:$H$1026,3,FALSE()) -> MUNICIPALIDAD DE JUNIN | C28: =VLOOKUP($A28,PRESUPUESTOS!$A$4:$H$1026,5,FALSE()) -> MANGUERA DESOBSTRUCTORA | D28: 45722 | F28: 8482882 | G28: =F28-E28 -> 8482882 | H28: PAGADO | I28: 45785 | J28: MANGUERA DE 3/4
B30: =VLOOKUP($A30,PRESUPUESTOS!$A$4:$H$1026,3,FALSE()) -> #N/A | C30: =VLOOKUP($A30,PRESUPUESTOS!$A$4:$H$1026,5,FALSE()) -> #N/A | G30: =F30-E30 -> 0
B31: =VLOOKUP($A31,PRESUPUESTOS!$A$4:$H$1026,3,FALSE()) -> #N/A | C31: =VLOOKUP($A31,PRESUPUESTOS!$A$4:$H$1026,5,FALSE()) -> #N/A | G31: =F31-E31 -> 0
B32: =VLOOKUP($A32,PRESUPUESTOS!$A$4:$H$1026,3,FALSE()) -> #N/A | C32: =VLOOKUP($A32,PRESUPUESTOS!$A$4:$H$1026,5,FALSE()) -> #N/A | G32: =F32-E32 -> 0
B33: =VLOOKUP($A33,PRESUPUESTOS!$A$4:$H$1026,3,FALSE()) -> #N/A | C33: =VLOOKUP($A33,PRESUPUESTOS!$A$4:$H$1026,5,FALSE()) -> #N/A | G33: =F33-E33 -> 0
B34: =VLOOKUP($A34,PRESUPUESTOS!$A$4:$H$1026,3,FALSE()) -> #N/A | C34: =VLOOKUP($A34,PRESUPUESTOS!$A$4:$H$1026,5,FALSE()) -> #N/A | G34: =F34-E34 -> 0
B35: =VLOOKUP($A35,PRESUPUESTOS!$A$4:$H$1026,3,FALSE()) -> #N/A | C35: =VLOOKUP($A35,PRESUPUESTOS!$A$4:$H$1026,5,FALSE()) -> #N/A | G35: =F35-E35 -> 0
B36: =VLOOKUP($A36,PRESUPUESTOS!$A$4:$H$1026,3,FALSE()) -> #N/A | C36: =VLOOKUP($A36,PRESUPUESTOS!$A$4:$H$1026,5,FALSE()) -> #N/A | G36: =F36-E36 -> 0
B37: =VLOOKUP($A37,PRESUPUESTOS!$A$4:$H$1026,3,FALSE()) -> #N/A | C37: =VLOOKUP($A37,PRESUPUESTOS!$A$4:$H$1026,5,FALSE()) -> #N/A | G37: =F37-E37 -> 0
B38: =VLOOKUP($A38,PRESUPUESTOS!$A$4:$H$1026,3,FALSE()) -> #N/A | C38: =VLOOKUP($A38,PRESUPUESTOS!$A$4:$H$1026,5,FALSE()) -> #N/A | G38: =F38-E38 -> 0
B39: =VLOOKUP($A39,PRESUPUESTOS!$A$4:$H$1026,3,FALSE()) -> #N/A | C39: =VLOOKUP($A39,PRESUPUESTOS!$A$4:$H$1026,5,FALSE()) -> #N/A | G39: =F39-E39 -> 0
B40: =VLOOKUP($A40,PRESUPUESTOS!$A$4:$H$1026,3,FALSE()) -> #N/A | C40: =VLOOKUP($A40,PRESUPUESTOS!$A$4:$H$1026,5,FALSE()) -> #N/A | G40: =F40-E40 -> 0
B41: =VLOOKUP($A41,PRESUPUESTOS!$A$4:$H$1026,3,FALSE()) -> #N/A | C41: =VLOOKUP($A41,PRESUPUESTOS!$A$4:$H$1026,5,FALSE()) -> #N/A | G41: =F41-E41 -> 0
... B51: =VLOOKUP($A51,PRESUPUESTOS!$A$4:$H$1026,3,FALSE()) -> #N/A | C51: =VLOOKUP($A51,PRESUPUESTOS!$A$4:$H$1026,5,FALSE()) -> #N/A | G51: =F51-E51 -> 0
E52: $30.213.890 | F52: $96.766.486 | G52: $66.552.596

Sheet 2024 Cotizaciones
A1: Nº | B1: FECHA | C1: CLIENTE | D1: EQUIPO - PATENTE | E1: DESCRIPCION | F1: A FACTURAR | G1: ESTADO | H1: OBSERVACIONES
A2: 248 | C2: INDUMAT V.C | D2: MV41 | F2: NO APROBADO | G2: NO APROBADO
A3: 2 | C3: INDUMAT | D3: JETSTREAM GAP01 | F3: NO APROBADO | G3: NO APROBADO
A4: 230 | B4: 45338 | C4: TRES ARROYOS | D4: - | E4: MANGUERA DESOBSTRUCTORA | F4: $ 6.006.056,81 | G4: APROBADO | H4: PAGADO, FINALIZADO.
A5: 1 | C5: SYL | D5: FURGON CHEVY VAN 30 | F5: $ 485.000,00 | G5: APROBADO
A6: 238 | B6: 45373 | C6: ABSA - LA PLATA | D6: AA-247-RA | F6: NO APLICA | G6: APROBADO | H6: SE VA PASAR EL PRESUPUESTO HASTA DONDE SE HIZO Y QUEDAN PENDIENTE ALGUNOS REPUESTOS PARA LA FINALIZACION
A7: 241 | B7: 45300 | C7: ABSA - LA PLATA | D7: AA-717-YH | F7: NO APLICA | G7: APROBADO | H7: TIENE QUE VOLVER A FORD PARA UN SENSOR (ESPERANDO RESPUESTA DE FORD)
A8: 245 | C8: SYL (La Plata) | D8: MV29 | F8: CLIENTE INTERNO | G8: COTIZADO
A9: 247 | C9: SYL (La Plata) | D9: MV26 | F9: CLIENTE INTERNO | G9: COTIZADO
A10: 242 | C10: ABSA | D10: AA-717-YL | E10: SE REALIZO UNA INSPECCION PARCIAL EN LA PLATA DE ABSA LA PLATA (SIN EFECTO, SE COBRA TODO JUNTO CON ACARREO) | F10: NO APLICA | G10: SIN EFECTO | H10: SE REALIZO UNA INSPECCION PARCIAL EN LA PLATA DE ABSA LA PLATA (SIN EFECTO, SE COBRA TODO JUNTO CON ACARREO)
A11: 246 | C11: SYL (La Plata) | D11: MV 25 | F11: PENDIENTE | G11: COTIZADO
A12: 243 | C12: ABSA | D12: AA-717-YM | E12: SE REALIZO UNA INSPECCION PARCIAL EN LA PLATA DE ABSA LA PLATA (SIN EFECTO, SE COBRA TODO JUNTO CON ACARREO) | F12: NO APLICA | G12: SIN EFECTO | H12: SE REALIZO UNA INSPECCION PARCIAL EN LA PLATA DE ABSA LA PLATA (SIN EFECTO, SE COBRA TODO JUNTO CON ACARREO)
A13: 244 | C13: ABSA | D13: ACARREO Y INSPECCION | E13: ACARREO Y INSPECCION DE CAMIONES DE ABSA (AA-717-YL, AA-717-YM) ESPERANDO CONFIRMACION | F13: 1.395.900 | G13: SIN EFECTO | H13: ACARREO Y INSPECCION DE CAMIONES DE ABSA (AA-717-YL, AA-717-YM) ESPERANDO CONFIRMACION
A14: 249 | B14: 45355 | C14: ABSA - REGION 5 | D14: AA-698-SW | E14: ARREGLO EN GENERAL, EN REPARACION | F14: ENVIADO | G14: APROBADO
A15: 250 | C15: SyL | D15: MV21 | F15: PENDIENTE | G15: COTIZADO
A16: 251 | B16: 45387 | C16: MUNI BERAZATEGUI | D16: VACTOR 2100 | E16: COTIZACION DE REPUESTO COLLAR ASSEMBLY TWIN DISC, ESPERANDO REPUESTA DEL CLIENTE | F16: 1400908.1 | G16: SIN EFECTO
A17: 252 | C17: MUNI MAR DEL PLATA | D17: JET-VAC 4075 | E17: MANGUERAS Y ACOPLES (CONCURSO DE PRECIOS, ESPERANDO RESPUESTA) | F17: 11637840 | G17: SIN EFECTO
A18: 253 | B18: 45483 | C18: MUNI MAR DEL PLATA OSSE | D18: JET-VAC 4075/4500 | E18: FILTROS Y VALVULAS | F18: ? | G18: COTIZADO
A19: 254 | C19: AGUAS RIONEGRINAS | D19: NO ESPECIFICO | E19: TOBERA SAPO 1" , ENVIADO ESPERANDO RESPUESTA. | F19: 366773 | G19: SIN EFECTO
A20: 255 | C20: ABSA | D20: JET-VAC 4075 | E20: ACARREO Y INSPECCION DE CAMIONES DE ABSA (AA-717-YL, AA-717-YM) | F20: 1395000 | G20: SIN EFECTO
A21: 256 | B21: 45426 | C21: SERVICOOP | D21: - | E21: MANGUERA DESOB 1" Y 3/4" | F21: $9.023.300,00 | G21: SIN EFECTO
A22: 257 | C22: INDUMAT | D22: PLANCHUELA | F22: 372000 | G22: SIN EFECTO
A23: 258 | C23: ABSA - LINCOLN | D23: JET VAC 4075 - AA-717-YI | E23: ARREGLOS EN GENERAL | F23: 20734574 | G23: APROBADO
A24: 259 | C24: FLUVIOMAT | D24: NO APLICA | F24: NO APLICA | G24: COTIZADO
A25: 260 | C25: INDUMAT | D25: MV09 | F25: NO APLICA | G25: SIN EFECTO
A26: 261 | C26: ABSA | D26: - | E26: MANGUERA DESOBSTRUCTORA 1" X 150MTS | F26: $6.460.238 | G26: COTIZADO
A27: 262 | C27: HR INDUSTRIAL | D27: NO APLICA | F27: $7.000.000 | G27: SIN EFECTO
A28: 263 | B28: 45441 | C28: SERVICIOS IBARRA | D28: - | E28: REJA CANASTO Y BOYA | F28: $800.000 (+IVA) | G28: APROBADO
A29: 264 | C29: INDUMAT | D29: MV33 | F29: $ 2.257.200,00
A30: 265 | B30: 45439 | C30: OSSE | D30: NO ESPECIFICO | E30: BOMBA KS40 | F30: $19.132.219,92 | G30: COTIZADO
A31: 266 | C31: ABSA | D31: 4075 (AA-717-YL) (AA-717-YM) | E31: ACARREO DE CAMIONES | F31: $880.000 (+IVA) | G31: APROBADO | H31: OC RECIBIDA EL 7/8 , FC ENVIADA
A32: 267 | B32: 45453 | C32: BENITO ROGGIO | D32: JET-VAC 5010 CB | E32: EQUIPO 0KM (4 CAMIONES) CONFIGURACION A | F32: USD 263.310 | G32: COTIZADO
A33: 268 | B33: 45453 | C33: BENITO ROGGIO | D33: JET-VAC 5010 CB | E33: EQUIPO 0KM (4 CAMIONES) CONFIGURACION B | F33: USD 275.563 | G33: COTIZADO
A34: 269 | B34: 45453 | C34: BENITO ROGGIO | D34: JET-VAC 5010 CB | E34: EQUIPO 0KM (4 CAMIONES) CONFIGURACION C | F34: USD 292.514 | G34: COTIZADO
A35: 270 | C35: AGUASSANTAFESINAS | D35: - | E35: 4 MANGUEROTES DE 8" | G35: SIN EFECTO
A36: 271 | C36: ABSA - LA PLATA | D36: AA-717-YH | E36: TERCERIZADO FORD CIRCUITO DE COMBUSTIBLE | F36: $1.980.000 | G36: APROBADO
A37: 272 | C37: INDUMAT | D37: FTS-456 | F37: 216HS | G37: COTIZADO
A38: 273 | C38: M. JUNIN | D38: Hidro JET 4500 | E38: MANGUERA DESOBSTRUCTORA 1" X 150MTS Y 3/4 MARCA ZEC ITALIA | F38: 14031084 | G38: SIN EFECTO
A39: 274 | C39: M.BERAZATEGUI | D39: JET-VAC 4075 | E39: RELAY 12V | F39: 471429 | G39: APROBADO
A40: 275 | C40: AUTOMAT - OBRAS | D40: CARRETON | F40: 1585644 | G40: COTIZADO
A41: 276 | C41: ABSA - CAÑUELAS | D41: JET-VAC 4075 | E41: SOPLADOR REPYCKY R3.8 (BLOWER) | F41: 34449607 | G41: COTIZADO | H41: BLOWER NUVO PARA EQUIPO AA-698-SW
A42: 277 | C42: HR INDUSTRIAL | D42: VACTOR 2100 | E42: CORONA DE GIRO DE CARRETEL VACTOR | F42: $7.223.437 | G42: SIN EFECTO | J42: FECHA
A43: 278 | C43: OSSE | D43: REPUESTOS VARIOS | G43: COTIZADO
A44: 279 | C44: AGUAS RIONEGRINAS | D44: VACTOR 2100 | E44: ENGRANAJES DE CAJA COTTA | F44: USD19.833 | G44: APROBADO
A45: 280 | C45: M. JUNIN | D45: JET VAC 4075? | E45: MANGUERA DESOBSTRUCTORA 1" | F45: $7.754.020 | G45: APROBADO | J45: 45338
A46: 281 | C46: OSSE | D46: JET-VAC 4075 | E46: BURLETE DE SELLO DE TANQUE | F46: 665400 | G46: APROBADO
A47: 282 | C47: SAMSA | D47: HIDROVACUO | E47: TOBERAS | F47: 2160404 | G47: SIN EFECTO | J47: 45373
A48: 283 | C48: SUMMIT NQN SA | D48: JET-VAC 5010 CB | E48: JET-VAC 5010 CB | F48: USD 263.310 | G48: COTIZADO | H48: EQUIPOS 0KM | J48: 45300
A49: 284 | C49: SUMMIT NQN SA | D49: JET-VAC 5010 CB | E49: JET-VAC 5010 CB | F49: USD 275.563 | G49: COTIZADO | H49: EQUIPOS 0KM
A50: 285 | C50: SUMMIT NQN SA | D50: JET-VAC 5010 CB | E50: JET-VAC 5010 CB | F50: USD 292.514 | G50: COTIZADO | H50: EQUIPOS 0KM
A51: 286 | C51: OSSE | D51: JET-VAC 4500-D | E51: FILTRO ACERO INOXIDABLE, RETENCION 200 MICRONES DE 70 H: 138MM ESTAÑADO | F51: 568200 | G51: APROBADO
A52: 287 | C52: M.JUNIN | D52: JET-VAC 4500-D | E52: FILTRO ACERO INOXIDABLE, RETENCION 200 MICRONES DE 70 H: 138MM ESTAÑADO, VALVULA DESVIAORA | F52: 1642817 | G52: APROBADO | H52: CONCRETADO!
A53: 288 | C53: AGUAS RIONEGRINAS | D53: VACTOR 2100 | E53: EMBRAGUE CAJA COTA | F53: USD 4.790 | G53: APROBADO | H53: CONCRETADO!
A54: 289 | C54: SERVICIOS IBARRA | D54: JET-VAC 4075 | E54: TANQUE DE AGUA LADO ACOMPAÑANTE SUPERIOR | F54: USD7400 | G54: COTIZADO
A55: 290 | B55: 45525 | C55: ABSA - LAS FLORES | D55: HIDROJET- SCORZA | E55: INSPECCION DE ARREGLOS EN GENERAL | F55: 34101996 | G55: APROBADO | H55: ADAPTACION DE BOMBA Y ARREGLOS EN GENERAL | J55: 45355
A56: 291 | B56: 45525 | C56: M.JUNIN | D56: JET-VAC-4075 | E56: INSPECCION Y ARREGLOS EN GENERAL | F56: 33505599 | G56: APROBADO | H56: REPARACIONES EN GENERAL
A57: 292 | B57: 45526 | C57: M. Trenque Lauquen | D57: SCORZA | E57: MANGUERA DESOBSTRUCTORA 1" | F57: 8537501 | G57: COTIZADO | H57: EN EL PRECIO ESTA INCLUIDO EL ENVIO | J57: 45387
A58: 293 | B58: 45527 | C58: M.JUNIN | D58: JET-VAC 4075 | E58: TOBERAS, GRANADA OVOIDAL 3/4 | F58: 1171799 | G58: APROBADO | H58: DOS TOBERAS GRANADA Y UNA OVOIDAL
A59: 294 | B59: 45532 | C59: M.BERAZATEGUI | D59: VACTOR 2100 | E59: REPARACION BOMBA DE AGUA | F59: 1176985 | G59: APROBADO | H59: ESPERANDO PAGO | J59: 45483
A60: 295 | B60: 45545 | C60: AGUAS RIONEGRINAS | D60: ABROCHADORA HIDRAULICA | E60: PRENSA PARA MANGUERAS HIDRAULICAS IN SITU | G60: COTIZADO | H60: SE COTIZO 3 OPCIONES DISTINTAS, ESPERANDO QUE DEFINA CUAL ES DE SU INTERES
A61: 296 | B61: 45545 | C61: AESA (YFP) | D61: JET-VAC 5010-CB | E61: CONFIGURACION A | F61: USD 263.310 | G61: COTIZADO | H61: EQUIPO 0KM
A62: 297 | B62: 45545 | C62: AESA (YFP) | D62: JET-VAC 5010-CB | E62: CONFIGURACION B | F62: USD 275.563 | G62: COTIZADO | H62: EQUIPO 0KM | J62: 45426
A63: 298 | B63: 45545 | C63: AESA (YFP) | D63: JET-VAC 5010-CB | E63: CONFIGURACION C | F63: USD 292.514 | G63: COTIZADO | H63: EQUIPO 0KM
A64: 299 | B64: 45552 | C64: EMSADE | D64: MANGUERA 1" | E64: MANGUERA DESOBSTRUCTORA 1" | F64: 8733415 | G64: COTIZADO | H64: MANGUERA DESOBSTRUCTORA
A65: 300 | B65: 45558 | C65: AGUAS DE FORMOSA | D65: N/A | E65: MANGUERA DE 12" | F65: USD 13.830 | G65: COTIZADO | H65: MANGUEROTE 12"
A66: 301 | B66: 45560 | C66: ABSA-CAÑUELAS | D66: JET-VAC 4075 | E66: CILINDRO DE TANQUE | F66: 6551015 | G66: COTIZADO | H66: CILINDRO ELEVACION TANQUE DE EQUIPO JET-VAC 4075
A67: 302 | B67: 45568 | C67: AESA (YFP) | D67: JET-VAC 5010 CB | E67: EQUIPO JET-VAC 5010 CB | F67: USD 250.121 | G67: COTIZADO | H67: EQUIPO 0KM
A68: 303 | B68: 45569 | C68: OSSE | D68: JET-VAC 4500-D | E68: CODO GIRATORIO | F68: 2855352 | G68: COTIZADO | H68: CODO GIRATORIO
A69: 304 | B69: 45569 | C69: OSSE | D69: JET-VAC 4500-D | E69: VALVULA DE TRES VIAS | F69: 501136 | G69: COTIZADO | H69: VALVULA DESVIADORA TRES VIAS | J69: 45441
A70: 305 | B70: 45569 | C70: SAMSA | D70: NO ESPECIFICO | E70: MANGUERA DESOBSTRUCTORA 1" | F70: 8100053 | G70: COTIZADO | H70: MANGUERA DESOBTRUCTORA 1"
A71: 306 | B71: 45570 | C71: AGUAS RIONEGRINAS | D71: JET-VAC 5010 | E71: EQUIPO JET-VAC 5010 CB CONFIGURACION A | F71: USD 242.739 | G71: COTIZADO | H71: EQUIPO 0KM | J71: 45439
A72: 307 | B72: 45570 | C72: AGUAS RIONEGRINAS | D72: JET-VAC 5010 | E72: EQUIPO JET-VAC 5010 CB CONFIGURACION B | F72: USD 254.034 | G72: COTIZADO | H72: EQUIPO 0KM
A73: 308 | B73: 45570 | C73: AGUAS RIONEGRINAS | D73: JET-VAC 5010 | E73: EQUIPO JET-VAC 5010 CB CONFIGURACION C | F73: USD 269.661 | G73: COTIZADO | H73: EQUIPO 0KM | J73: 45453
A74: 309 | B74: 45573 | C74: HR INDUSTRIAL | D74: REPUESTO | E74: VACTOR 2100 | F74: 7945780 | G74: COTIZADO | H74: RODAMIENTO PARA CARRETEL VACTOR | J74: 45453
A75: 310 | B75: 45582 | C75: ABSA - LA PLATA | D75: JET-VAC 4075 | E75: ARREGLOS EN GENERAL | F75: 22243813 | G75: APROBADO | H75: REPARACION DE EMBRAGUE Y ARREGLOS EN GENERAL | J75: 45453
A76: 311 | B76: 45587 | C76: MUNICIPALIDAD DE SALADILLO | D76: NO ESPECIFICO | E76: MANGUERA , TOBERAS | F76: 20872166 | G76: COTIZADO | H76: MANGUERAS DESOB DE 1" Y 3/4 MARCA ZEC
A77: 312 | B77: 45589 | C77: OSSE | D77: JET-VAC 4500-D | E77: CODO GIRATORIO 1" | F77: 3454975 | G77: COTIZADO | H77: DOS CODOS GIRATORIOS DE 1" PARA EQUIPO JET-VAC 4500-D
A78: 313 | B78: 45589 | C78: SCPL | D78: ITECSA | E78: TOBERAS Y ABRAZADERAS | F78: 9869493 | G78: APROBADO | H78: MANGUERAS DESOB DE 1", TOBERAS, ABRAZADERAS, MANGUEROTE 8" 7m
A79: 314 | B79: 45596 | C79: M.BERAZATEGUI | D79: VACTOR 2100 | E79: REPARACION DE BOMBA RODER | F79: 3870363 | G79: APROBADO | H79: REPARACION EN GENERAL DE BOMBA
A80: 315 | B80: 45601 | C80: ABSA - LA PLATA | D80: JET-VAC 4075 | E80: REPARACION EN GENERAL | F80: 28553207 | G80: APROBADO | H80: REPARACION EN GENERAL PARA EQUIPO
A81: 316 | B81: 45602 | C81: MUNICIPALIDAD DE JUNIN | D81: JET-VAC 4500-D | E81: MANGUERA DE 3/4 DESOBSTRUCTORA | F81: 7612098 | G81: COTIZADO | H81: MANGUERA DE CARRETEL
A82: 317 | B82: 45608 | C82: MUNICIPALIDAD DE TRES ARROYOS | D82: VACTOR 2100 | E82: REPARACION EN GENERAL | F82: 18164210 | G82: APROBADO | H82: REPARACION DE EQUIPO EN GENERAL
A83: 318 | B83: 45609 | C83: OSSE | D83: NO ESPECIFICO | E83: MANGUEROTE DE SUBCCION 8" | F83: 870295 | G83: COTIZADO | H83: MANGUEROTE DE PLUMA
A84: 319 | B84: 45615 | C84: AGUAS RIONEGRINAS | D84: NO ESPECIFICO | E84: CODO GIRATORIO 1" , MANGUEROTE DE 8" | F84: 1994726 | G84: COTIZADO | H84: CODO GIRATORIO Y MANGUEROTE DE SUBCCION DE PLUMA
